arclet/edoves/__init__.py
arclet/edoves/builtin/__init__.py
arclet/edoves/builtin/actions.py
arclet/edoves/builtin/alconna.py
arclet/edoves/builtin/behavior.py
arclet/edoves/builtin/client.py
arclet/edoves/builtin/commander.py
arclet/edoves/builtin/filter.py
arclet/edoves/builtin/medium.py
arclet/edoves/builtin/event/__init__.py
arclet/edoves/builtin/event/lifecycle.py
arclet/edoves/builtin/event/message.py
arclet/edoves/builtin/event/network.py
arclet/edoves/builtin/event/notice.py
arclet/edoves/builtin/message/__init__.py
arclet/edoves/builtin/message/chain.py
arclet/edoves/builtin/message/element.py
arclet/edoves/builtin/timer/__init__.py
arclet/edoves/builtin/timer/timers.py
arclet/edoves/mah/__init__.py
arclet/edoves/mah/actions.py
arclet/edoves/mah/chain.py
arclet/edoves/mah/elements.py
arclet/edoves/mah/filter.py
arclet/edoves/mah/monomers.py
arclet/edoves/mah/protocol.py
arclet/edoves/mah/server_docker.py
arclet/edoves/mah/module/__init__.py
arclet/edoves/mah/module/message.py
arclet/edoves/mah/parsers/__init__.py
arclet/edoves/mah/parsers/message.py
arclet/edoves/mah/parsers/request.py
arclet/edoves/mah/parsers/notice/__init__.py
arclet/edoves/mah/parsers/notice/bot.py
arclet/edoves/mah/parsers/notice/friend.py
arclet/edoves/mah/parsers/notice/group.py
arclet/edoves/mah/parsers/notice/member.py
arclet/edoves/main/__init__.py
arclet/edoves/main/action.py
arclet/edoves/main/config.py
arclet/edoves/main/context.py
arclet/edoves/main/event.py
arclet/edoves/main/exceptions.py
arclet/edoves/main/medium.py
arclet/edoves/main/network.py
arclet/edoves/main/protocol.py
arclet/edoves/main/scene.py
arclet/edoves/main/screen.py
arclet/edoves/main/typings.py
arclet/edoves/main/component/__init__.py
arclet/edoves/main/component/behavior.py
arclet/edoves/main/interact/__init__.py
arclet/edoves/main/interact/module.py
arclet/edoves/main/interact/monomer.py
arclet/edoves/main/interact/parser.py
arclet/edoves/main/interact/server_docker.py
arclet_edoves-0.0.18.dist-info/LICENSE
arclet_edoves-0.0.18.dist-info/METADATA
arclet_edoves-0.0.18.dist-info/WHEEL
arclet_edoves-0.0.18.dist-info/top_level.txt
arclet_edoves-0.0.18.dist-info/RECORD
