Metadata-Version: 2.1
Name: arclet-edoves
Version: 0.0.18
Summary: A new abstract framework based on Cesloi 
Home-page: https://github.com/ArcletProject/Edoves
Author: ArcletProject
Author-email: rf_tar_railt@qq.com
License: MIT
Keywords: mirai,bot,asyncio,http,websocket
Platform: UNKNOWN
Classifier: Programming Language :: Python :: 3.8
Classifier: Programming Language :: Python :: 3.9
Classifier: Programming Language :: Python :: 3.10
Classifier: Operating System :: OS Independent
Requires-Python: >=3.8
License-File: LICENSE
Requires-Dist: aiohttp
Requires-Dist: yarl
Requires-Dist: pydantic
Requires-Dist: loguru
Requires-Dist: arclet-letoderea
Requires-Dist: arclet-alconna
Requires-Dist: importlib-metadata
